sapl_base/__init__.py
sapl_base/authorization_subscription_factory.py
sapl_base/authorization_subscriptions.py
sapl_base/base_authorization_subscription_factory.py
sapl_base/decision.py
sapl_base/decorators.py
sapl_base/exceptions.py
sapl_base/policy_decision_points.py
sapl_base/sapl_util.py
sapl_base/constraint_handling/__init__.py
sapl_base/constraint_handling/constraint_handler_bundle.py
sapl_base/constraint_handling/constraint_handler_provider.py
sapl_base/constraint_handling/constraint_handler_service.py
sapl_base/policy_enforcement_points/__init__.py
sapl_base/policy_enforcement_points/async_generator_policy_enforcement_point.py
sapl_base/policy_enforcement_points/async_policy_enforcement_point.py
sapl_base/policy_enforcement_points/policy_enforcement_point.py
sapl_base/policy_enforcement_points/streaming_policy_enforcement_point.py
sapl_base/policy_enforcement_points/sync_policy_enforcement_point.py
SAPL_Base-0.3.6.dist-info/LICENSE
SAPL_Base-0.3.6.dist-info/METADATA
SAPL_Base-0.3.6.dist-info/WHEEL
SAPL_Base-0.3.6.dist-info/top_level.txt
SAPL_Base-0.3.6.dist-info/RECORD
