Metadata-Version: 2.1
Name: SAPL-Base
Version: 0.3.6
Summary: Base library to create SAPL Integrations for Python Frameworks
Author-email: Dominic Heutelbeck <dominic@heutelbeck.com>
License: Copyright 2017-2022 Dominic Heutelbeck
Project-URL: Homepage, https://sapl.io/
Project-URL: Documentation, https://sapl.io/documentation
Project-URL: Source, https://github.com/heutelbeck/sapl-python/tree/master/sapl_base
License-File: LICENSE
Requires-Dist: backoff
Requires-Dist: aiohttp
Requires-Dist: requests
Requires-Dist: pytest
Requires-Dist: asgiref
Requires-Dist: sseclient-py
Provides-Extra: tests
Requires-Dist: pytest-asyncio ; extra == 'tests'
